doot/__init__.py
doot/bot.py
doot/callback.py
doot/command_handler.py
doot/exception.py
doot/message.py
doot/message_handler.py
doot/response.py
dooth-1.1.9.dist-info/METADATA
dooth-1.1.9.dist-info/WHEEL
dooth-1.1.9.dist-info/top_level.txt
dooth-1.1.9.dist-info/RECORD
